{
  "experiment": "SWARM-04",
  "goal": "Prove k=2 fails when \u03ba < 25",
  "timestamp": "2026-03-13T17:39:56.081826",
  "results": [
    {
      "strategy": "high_variance",
      "dim": 64,
      "concentration": 0.7,
      "n_samples": 300,
      "stable_rank": 12.7,
      "kappa": 5.04,
      "k_optimal": 5,
      "k2_works": false,
      "k2_fails": true
    },
    {
      "strategy": "high_variance",
      "dim": 64,
      "concentration": 0.8,
      "n_samples": 300,
      "stable_rank": 7.96,
      "kappa": 8.04,
      "k_optimal": 5,
      "k2_works": false,
      "k2_fails": true
    },
    {
      "strategy": "high_variance",
      "dim": 64,
      "concentration": 0.9,
      "n_samples": 300,
      "stable_rank": 5.8,
      "kappa": 11.03,
      "k_optimal": 5,
      "k2_works": false,
      "k2_fails": true
    },
    {
      "strategy": "high_variance",
      "dim": 128,
      "concentration": 0.7,
      "n_samples": 300,
      "stable_rank": 22.92,
      "kappa": 5.58,
      "k_optimal": 5,
      "k2_works": false,
      "k2_fails": true
    },
    {
      "strategy": "high_variance",
      "dim": 128,
      "concentration": 0.8,
      "n_samples": 300,
      "stable_rank": 13.79,
      "kappa": 9.29,
      "k_optimal": 5,
      "k2_works": false,
      "k2_fails": true
    },
    {
      "strategy": "high_variance",
      "dim": 128,
      "concentration": 0.9,
      "n_samples": 300,
      "stable_rank": 9.52,
      "kappa": 13.44,
      "k_optimal": 5,
      "k2_works": false,
      "k2_fails": true
    },
    {
      "strategy": "high_variance",
      "dim": 256,
      "concentration": 0.7,
      "n_samples": 300,
      "stable_rank": 39.76,
      "kappa": 6.44,
      "k_optimal": 5,
      "k2_works": false,
      "k2_fails": true
    },
    {
      "strategy": "high_variance",
      "dim": 256,
      "concentration": 0.8,
      "n_samples": 300,
      "stable_rank": 23.72,
      "kappa": 10.79,
      "k_optimal": 5,
      "k2_works": false,
      "k2_fails": true
    },
    {
      "strategy": "high_variance",
      "dim": 256,
      "concentration": 0.9,
      "n_samples": 300,
      "stable_rank": 17.13,
      "kappa": 14.94,
      "k_optimal": 5,
      "k2_works": false,
      "k2_fails": true
    },
    {
      "strategy": "clustered",
      "dim": 64,
      "n_clusters": 10,
      "n_samples": 300,
      "stable_rank": 5.52,
      "kappa": 11.59,
      "k_optimal": 5,
      "k2_works": false,
      "k2_fails": true
    },
    {
      "strategy": "clustered",
      "dim": 64,
      "n_clusters": 20,
      "n_samples": 300,
      "stable_rank": 9.45,
      "kappa": 6.77,
      "k_optimal": 5,
      "k2_works": false,
      "k2_fails": true
    },
    {
      "strategy": "clustered",
      "dim": 64,
      "n_clusters": 30,
      "n_samples": 300,
      "stable_rank": 11.41,
      "kappa": 5.61,
      "k_optimal": 5,
      "k2_works": false,
      "k2_fails": true
    },
    {
      "strategy": "clustered",
      "dim": 128,
      "n_clusters": 10,
      "n_samples": 300,
      "stable_rank": 6.15,
      "kappa": 20.8,
      "k_optimal": 4,
      "k2_works": false,
      "k2_fails": true
    },
    {
      "strategy": "clustered",
      "dim": 128,
      "n_clusters": 20,
      "n_samples": 300,
      "stable_rank": 10.8,
      "kappa": 11.85,
      "k_optimal": 5,
      "k2_works": false,
      "k2_fails": true
    },
    {
      "strategy": "clustered",
      "dim": 128,
      "n_clusters": 30,
      "n_samples": 300,
      "stable_rank": 13.39,
      "kappa": 9.56,
      "k_optimal": 5,
      "k2_works": false,
      "k2_fails": true
    },
    {
      "strategy": "clustered",
      "dim": 256,
      "n_clusters": 10,
      "n_samples": 300,
      "stable_rank": 6.37,
      "kappa": 40.21,
      "k_optimal": 2,
      "k2_works": true,
      "k2_fails": false
    },
    {
      "strategy": "clustered",
      "dim": 256,
      "n_clusters": 20,
      "n_samples": 300,
      "stable_rank": 13.05,
      "kappa": 19.61,
      "k_optimal": 4,
      "k2_works": false,
      "k2_fails": true
    },
    {
      "strategy": "clustered",
      "dim": 256,
      "n_clusters": 30,
      "n_samples": 300,
      "stable_rank": 17.7,
      "kappa": 14.46,
      "k_optimal": 5,
      "k2_works": false,
      "k2_fails": true
    },
    {
      "strategy": "real_model",
      "model": "all-MiniLM-L6-v2",
      "dim": 384,
      "n_samples": 325,
      "stable_rank": 7.81,
      "kappa": 49.17,
      "k_optimal": 2,
      "k2_works": true,
      "k2_fails": false
    },
    {
      "strategy": "real_model",
      "model": "paraphrase-albert-small-v2",
      "dim": 768,
      "n_samples": 325,
      "stable_rank": 6.66,
      "kappa": 115.25,
      "k_optimal": 1,
      "k2_works": true,
      "k2_fails": false
    },
    {
      "strategy": "real_model",
      "model": "average_word_embeddings_glove.6B.300d",
      "dim": 300,
      "n_samples": 325,
      "stable_rank": 5.13,
      "kappa": 58.52,
      "k_optimal": 1,
      "k2_works": true,
      "k2_fails": false
    }
  ],
  "summary": {
    "total_tests": 21,
    "k2_failures": 17,
    "k2_failure_rate": 81.0
  },
  "failure_cases": [
    {
      "strategy": "high_variance",
      "dim": 64,
      "concentration": 0.7,
      "n_samples": 300,
      "stable_rank": 12.7,
      "kappa": 5.04,
      "k_optimal": 5,
      "k2_works": false,
      "k2_fails": true
    },
    {
      "strategy": "high_variance",
      "dim": 64,
      "concentration": 0.8,
      "n_samples": 300,
      "stable_rank": 7.96,
      "kappa": 8.04,
      "k_optimal": 5,
      "k2_works": false,
      "k2_fails": true
    },
    {
      "strategy": "high_variance",
      "dim": 64,
      "concentration": 0.9,
      "n_samples": 300,
      "stable_rank": 5.8,
      "kappa": 11.03,
      "k_optimal": 5,
      "k2_works": false,
      "k2_fails": true
    },
    {
      "strategy": "high_variance",
      "dim": 128,
      "concentration": 0.7,
      "n_samples": 300,
      "stable_rank": 22.92,
      "kappa": 5.58,
      "k_optimal": 5,
      "k2_works": false,
      "k2_fails": true
    },
    {
      "strategy": "high_variance",
      "dim": 128,
      "concentration": 0.8,
      "n_samples": 300,
      "stable_rank": 13.79,
      "kappa": 9.29,
      "k_optimal": 5,
      "k2_works": false,
      "k2_fails": true
    },
    {
      "strategy": "high_variance",
      "dim": 128,
      "concentration": 0.9,
      "n_samples": 300,
      "stable_rank": 9.52,
      "kappa": 13.44,
      "k_optimal": 5,
      "k2_works": false,
      "k2_fails": true
    },
    {
      "strategy": "high_variance",
      "dim": 256,
      "concentration": 0.7,
      "n_samples": 300,
      "stable_rank": 39.76,
      "kappa": 6.44,
      "k_optimal": 5,
      "k2_works": false,
      "k2_fails": true
    },
    {
      "strategy": "high_variance",
      "dim": 256,
      "concentration": 0.8,
      "n_samples": 300,
      "stable_rank": 23.72,
      "kappa": 10.79,
      "k_optimal": 5,
      "k2_works": false,
      "k2_fails": true
    },
    {
      "strategy": "high_variance",
      "dim": 256,
      "concentration": 0.9,
      "n_samples": 300,
      "stable_rank": 17.13,
      "kappa": 14.94,
      "k_optimal": 5,
      "k2_works": false,
      "k2_fails": true
    },
    {
      "strategy": "clustered",
      "dim": 64,
      "n_clusters": 10,
      "n_samples": 300,
      "stable_rank": 5.52,
      "kappa": 11.59,
      "k_optimal": 5,
      "k2_works": false,
      "k2_fails": true
    },
    {
      "strategy": "clustered",
      "dim": 64,
      "n_clusters": 20,
      "n_samples": 300,
      "stable_rank": 9.45,
      "kappa": 6.77,
      "k_optimal": 5,
      "k2_works": false,
      "k2_fails": true
    },
    {
      "strategy": "clustered",
      "dim": 64,
      "n_clusters": 30,
      "n_samples": 300,
      "stable_rank": 11.41,
      "kappa": 5.61,
      "k_optimal": 5,
      "k2_works": false,
      "k2_fails": true
    },
    {
      "strategy": "clustered",
      "dim": 128,
      "n_clusters": 10,
      "n_samples": 300,
      "stable_rank": 6.15,
      "kappa": 20.8,
      "k_optimal": 4,
      "k2_works": false,
      "k2_fails": true
    },
    {
      "strategy": "clustered",
      "dim": 128,
      "n_clusters": 20,
      "n_samples": 300,
      "stable_rank": 10.8,
      "kappa": 11.85,
      "k_optimal": 5,
      "k2_works": false,
      "k2_fails": true
    },
    {
      "strategy": "clustered",
      "dim": 128,
      "n_clusters": 30,
      "n_samples": 300,
      "stable_rank": 13.39,
      "kappa": 9.56,
      "k_optimal": 5,
      "k2_works": false,
      "k2_fails": true
    },
    {
      "strategy": "clustered",
      "dim": 256,
      "n_clusters": 20,
      "n_samples": 300,
      "stable_rank": 13.05,
      "kappa": 19.61,
      "k_optimal": 4,
      "k2_works": false,
      "k2_fails": true
    },
    {
      "strategy": "clustered",
      "dim": 256,
      "n_clusters": 30,
      "n_samples": 300,
      "stable_rank": 17.7,
      "kappa": 14.46,
      "k_optimal": 5,
      "k2_works": false,
      "k2_fails": true
    }
  ],
  "patent_evidence": {
    "adila_limitation": "Fixed k=2, no \u03ba diagnostic",
    "our_contribution": "\u03ba measurement + optimal k formula",
    "differentiation": "17 cases where k=2 insufficient"
  },
  "proof_status": "PROVEN"
}